{
"type": "FeatureCollection",
"name": "wildlife_risk_assessed",
"crs": { "type": "name", "properties": { "name": "urn:ogc:def:crs:OGC:1.3:CRS84" } },
"features": [
{ "type": "Feature", "properties": { "name": "Ijara Hirola Sanctuary", "animal": "Hirola Antelope", "status": "Critically Endangered", "description": "Critical sanctuary for the rarest antelope in the world. Autogeoreferenced habitat corridor.", "sub_county": "Ijara Sub County", "population_est": "250", "Risk_Level": "Safe", "Distance_to_Flood_km": "6.85", "Poverty_Rate": "0.62", "Food_Poverty_Rate": "0.45", "Wasting_Rate": "0.12", "Avg_HH_Income": "5169", "Avg_HH_Expenditure": "6177", "HH_Cash_Gap": "-1008", "Post_Assistance_Income": "13927", "Post_Assistance_Expenditure": "11092", "Post_Assistance_Surplus": "2835", "Vulnerability_Index": "0.339", "marker_emoji": "🦒", "Author": "Garissa GIS Directorate — James M. Mburu", "NN_Vulnerability_Score": "0.323", "NN_Risk_Class": "Medium" }, "geometry": { "type": "Point", "coordinates": [ 40.4, -1.6 ] } },
{ "type": "Feature", "properties": { "name": "Fafi Elephant Corridor", "animal": "African Elephant", "status": "Endangered", "description": "Boni Forest border corridor supporting endangered elephant herds.", "sub_county": "Fafi Sub County", "population_est": "120", "Risk_Level": "Safe", "Distance_to_Flood_km": "8.94", "Poverty_Rate": "0.77", "Food_Poverty_Rate": "0.57", "Wasting_Rate": "0.14", "Avg_HH_Income": "5169", "Avg_HH_Expenditure": "6177", "HH_Cash_Gap": "-1008", "Post_Assistance_Income": "13927", "Post_Assistance_Expenditure": "11092", "Post_Assistance_Surplus": "2835", "Vulnerability_Index": "0.366", "marker_emoji": "🦒", "Author": "Garissa GIS Directorate — James M. Mburu", "NN_Vulnerability_Score": "0.313", "NN_Risk_Class": "Medium" }, "geometry": { "type": "Point", "coordinates": [ 40.14, -1.08 ] } },
{ "type": "Feature", "properties": { "name": "Township Somali Ostrich Zone", "animal": "Somali Ostrich", "status": "Least Concern", "description": "Dry scrublands housing Somali ostrich families.", "sub_county": "Garissa Sub County", "population_est": "350", "Risk_Level": "Safe", "Distance_to_Flood_km": "8.0", "Poverty_Rate": "0.48", "Food_Poverty_Rate": "0.35", "Wasting_Rate": "0.1", "Avg_HH_Income": "5169", "Avg_HH_Expenditure": "6177", "HH_Cash_Gap": "-1008", "Post_Assistance_Income": "13927", "Post_Assistance_Expenditure": "11092", "Post_Assistance_Surplus": "2835", "Vulnerability_Index": "0.254", "marker_emoji": "🦒", "Author": "Garissa GIS Directorate — James M. Mburu", "NN_Vulnerability_Score": "0.229", "NN_Risk_Class": "Low" }, "geometry": { "type": "Point", "coordinates": [ 39.68, -0.35 ] } },
{ "type": "Feature", "properties": { "name": "Balambala Cheetah Plains", "animal": "Cheetah", "status": "Vulnerable", "description": "Dry savanna hunting plains supporting cheetah prides.", "sub_county": "Balambala Sub County", "population_est": "45", "Risk_Level": "Medium Risk", "Distance_to_Flood_km": "0.8", "Poverty_Rate": "0.82", "Food_Poverty_Rate": "0.62", "Wasting_Rate": "0.15", "Avg_HH_Income": "5169", "Avg_HH_Expenditure": "6177", "HH_Cash_Gap": "-1008", "Post_Assistance_Income": "13927", "Post_Assistance_Expenditure": "11092", "Post_Assistance_Surplus": "2835", "Vulnerability_Index": "0.704", "marker_emoji": "🦒", "Author": "Garissa GIS Directorate — James M. Mburu", "NN_Vulnerability_Score": "0.551", "NN_Risk_Class": "High" }, "geometry": { "type": "Point", "coordinates": [ 39.63, -0.04 ] } }
]
}
